{
  "source": "gdelt",
  "fetchedAt": "2026-03-23T11:49:53.139Z",
  "indicators": [
    {
      "countryIso3": "AFG",
      "indicatorName": "gdelt_instability",
      "value": 0.7348766666666666,
      "year": 2026,
      "source": "gdelt"
    },
    {
      "countryIso3": "DZA",
      "indicatorName": "gdelt_instability",
      "value": 0.6658807999999999,
      "year": 2026,
      "source": "gdelt"
    },
    {
      "countryIso3": "BLR",
      "indicatorName": "gdelt_instability",
      "value": 0.5472133333333333,
      "year": 2026,
      "source": "gdelt"
    },
    {
      "countryIso3": "CAN",
      "indicatorName": "gdelt_instability",
      "value": 0.5106233333333333,
      "year": 2026,
      "source": "gdelt"
    },
    {
      "countryIso3": "CHN",
      "indicatorName": "gdelt_instability",
      "value": 0.4090476,
      "year": 2026,
      "source": "gdelt"
    },
    {
      "countryIso3": "COL",
      "indicatorName": "gdelt_instability",
      "value": 0.7037852,
      "year": 2026,
      "source": "gdelt"
    },
    {
      "countryIso3": "EGY",
      "indicatorName": "gdelt_instability",
      "value": 0.54005,
      "year": 2026,
      "source": "gdelt"
    },
    {
      "countryIso3": "IRQ",
      "indicatorName": "gdelt_instability",
      "value": 0.9582892,
      "year": 2026,
      "source": "gdelt"
    },
    {
      "countryIso3": "KOR",
      "indicatorName": "gdelt_instability",
      "value": 0.5672556,
      "year": 2026,
      "source": "gdelt"
    },
    {
      "countryIso3": "MEX",
      "indicatorName": "gdelt_instability",
      "value": 0.5831566666666667,
      "year": 2026,
      "source": "gdelt"
    },
    {
      "countryIso3": "SAU",
      "indicatorName": "gdelt_instability",
      "value": 0.29201,
      "year": 2026,
      "source": "gdelt"
    },
    {
      "countryIso3": "SOM",
      "indicatorName": "gdelt_instability",
      "value": 0.8210496,
      "year": 2026,
      "source": "gdelt"
    },
    {
      "countryIso3": "SYR",
      "indicatorName": "gdelt_instability",
      "value": 0.8123584,
      "year": 2026,
      "source": "gdelt"
    },
    {
      "countryIso3": "THA",
      "indicatorName": "gdelt_instability",
      "value": 0.5096324,
      "year": 2026,
      "source": "gdelt"
    },
    {
      "countryIso3": "VNM",
      "indicatorName": "gdelt_instability",
      "value": 0.47553480000000004,
      "year": 2026,
      "source": "gdelt"
    }
  ]
}
